paramspace/__init__.py
paramspace/paramdim.py
paramspace/paramspace.py
paramspace/tools.py
paramspace/yaml.py
paramspace/yaml_constructors.py
paramspace/yaml_representers.py
paramspace-2.8.2.data/data/CHANGELOG.md
paramspace-2.8.2.data/data/LICENSE
paramspace-2.8.2.data/data/README.md
paramspace-2.8.2.dist-info/licenses/LICENSE
paramspace-2.8.2.dist-info/METADATA
paramspace-2.8.2.dist-info/WHEEL
paramspace-2.8.2.dist-info/top_level.txt
paramspace-2.8.2.dist-info/RECORD
