Metadata-Version: 2.4
Name: paramspace
Version: 2.8.2
Summary: Dictionary-based, multi-dimensional parameter space iteration
Home-page: https://gitlab.com/blsqr/paramspace
Author: Yunus Sevinchan
Author-email: yunussevinchan@gmail.com
License: BSD-2-Clause
Classifier: Development Status :: 5 - Production/Stable
Classifier: Intended Audience :: Science/Research
Classifier: License :: OSI Approved :: BSD License
Classifier: Programming Language :: Python :: 3
Classifier: Programming Language :: Python :: 3 :: Only
Classifier: Programming Language :: Python :: 3.6
Classifier: Programming Language :: Python :: 3.7
Classifier: Programming Language :: Python :: 3.8
Classifier: Programming Language :: Python :: 3.9
Classifier: Programming Language :: Python :: 3.10
Classifier: Programming Language :: Python :: 3.11
Classifier: Programming Language :: Python :: 3.12
Classifier: Programming Language :: Python :: 3.13
Classifier: Programming Language :: Python :: 3.14
Classifier: Topic :: Utilities
Classifier: Typing :: Typed
Requires-Python: >=3.6
License-File: LICENSE
Requires-Dist: numpy
Requires-Dist: xarray
Requires-Dist: ruamel.yaml
Requires-Dist: yayaml>=0.2.1
Provides-Extra: test
Requires-Dist: tox; extra == "test"
Requires-Dist: pytest; extra == "test"
Requires-Dist: pytest-cov; extra == "test"
Provides-Extra: dev
Requires-Dist: pre-commit; extra == "dev"
Requires-Dist: seed-isort-config; extra == "dev"
Requires-Dist: isort[pyproject]; extra == "dev"
Requires-Dist: black; extra == "dev"
Requires-Dist: pyupgrade; extra == "dev"
Provides-Extra: doc
Requires-Dist: sphinx==5.*; extra == "doc"
Requires-Dist: sphinx-book-theme; extra == "doc"
Requires-Dist: sphinx-togglebutton; extra == "doc"
Requires-Dist: ipython; extra == "doc"
Dynamic: author
Dynamic: author-email
Dynamic: classifier
Dynamic: description
Dynamic: home-page
Dynamic: license
Dynamic: license-file
Dynamic: provides-extra
Dynamic: requires-dist
Dynamic: requires-python
Dynamic: summary
